{
    "student_id": "2023130566",
    "name": "약게젓",
    "image": "images/yakgaejut.png",
    "image_prompt": "다음은 약게젓 레시피야. 예상되는 완성된 음식을 상상해서 그려줘. 간장에 반쯤 담아져 있어야해. 게가 쉰 마리 정도이면 진간장 두 되, 참기름 한 되에 생강, 후추, 천초를 교합(交合)하여 짜게 달여서 식히고, 게를 깨끗이 씻어 이틀 정도 굶겨서 그 국에 담가 익으면 쓴다.",
    "ingredients": [
        "게",
        "진간장",
        "참기름",
        "생강",
        "후추",
        "천초"
    ],
    "original": "게 쉰 마리만 ᄒᆞ거든 젼지령 두 되 ᄎᆞᆷ기ᄅᆞᆷ ᄒᆞᆫ 되예 ᄉᆡᆼ강 호쵸 쳔쵸 ?교합ᄒᆞ여 ᄧᆞ게달혀 씨기고 게ᄅᆞᆯ 조히 시어 이트리나 주우리거든 그 국의 ᄃᆞᆷ가 닉거든 쓰ᄂᆞ니라.",
    "translated": "게가 쉰 마리 정도이면 진간장 두 되, 참기름 한 되에 생강, 후추, 천초를 교합(交合)하여 짜게 달여서 식히고, 게를 깨끗이 씻어 이틀 정도 굶겨서 그 국에 담가 익으면 쓴다.",
    "source": "음식디미방",
    "comment": "지금 우리가 먹는 간장게장과 다른 점, 게를 이틀 정도 굶긴다는 것이 신기했다."
}